about_me/__init__.py
about_me/about_me.py
About_ak_dev-1.0.dist-info/METADATA
About_ak_dev-1.0.dist-info/WHEEL
About_ak_dev-1.0.dist-info/top_level.txt
About_ak_dev-1.0.dist-info/RECORD
