Metadata-Version: 2.1
Name: About_ak_dev
Version: 1.0
Summary: This package contains data about Ak dev
